{
  "references": [
    {
      "title": "The Reactome Pathway Knowledgebase",
      "year": 2018,
      "journal": "Nucleic Acids Res",
      "volume": 46,
      "pages": "D649-D655",
      "pubMedIdentifier": 29145629,
      "author": [
        {
          "firstname": "Antonio",
          "surname": "Fabregat",
          "displayName": "Fabregat, A"
        },
        {
          "firstname": "Steven",
          "surname": "Jupe",
          "displayName": "Jupe, S"
        },
        {
          "firstname": "Lisa",
          "surname": "Matthews",
          "displayName": "Matthews, L"
        },
        {
          "firstname": "Konstantinos",
          "surname": "Sidiropoulos",
          "displayName": "Sidiropoulos, K"
        },
        {
          "firstname": "Marc",
          "surname": "Gillespie",
          "displayName": "Gillespie, M"
        },
        {
          "firstname": "Phani",
          "surname": "Garapati",
          "displayName": "Garapati, P"
        },
        {
          "firstname": "Robin",
          "surname": "Haw",
          "displayName": "Haw, R"
        },
        {
          "firstname": "Bijay",
          "surname": "Jassal",
          "displayName": "Jassal, B"
        },
        {
          "firstname": "Florian",
          "surname": "Korninger",
          "displayName": "Korninger, F"
        },
        {
          "firstname": "Bruce",
          "surname": "May",
          "displayName": "May, B"
        },
        {
          "firstname": "Marija",
          "surname": "Milacic",
          "displayName": "Milacic, M"
        },
        {
          "firstname": "Corina",
          "surname": "Duenas",
          "displayName": "Duenas, C"
        },
        {
          "firstname": "Karen",
          "surname": "Rothfels",
          "displayName": "Rothfels, K"
        },
        {
          "firstname": "Cristoffer",
          "surname": "Sevilla",
          "displayName": "Sevilla, C"
        },
        {
          "firstname": "Veronica",
          "surname": "Shamovsky",
          "displayName": "Shamovsky, V"
        },
        {
          "firstname": "Solomon",
          "surname": "Shorser",
          "displayName": "Shorser, S"
        },
        {
          "firstname": "Thawfeek",
          "surname": "Varusai",
          "displayName": "Varusai, T"
        },
        {
          "firstname": "Guilherme",
          "surname": "Viteri",
          "displayName": "Viteri, G"
        },
        {
          "firstname": "Joel",
          "surname": "Weiser",
          "displayName": "Weiser, J"
        },
        {
          "firstname": "Guanming",
          "surname": "Wu",
          "displayName": "Wu, G"
        },
        {
          "firstname": "Lincoln",
          "surname": "Stein",
          "displayName": "Stein, L"
        },
        {
          "firstname": "Henning",
          "surname": "Hermjakob",
          "displayName": "Hermjakob, H"
        },
        {
          "firstname": "Peter",
          "surname": "D'Eustachio",
          "displayName": "D'Eustachio, P"
        }
      ]
    },
    {
      "title": "Reactome pathway analysis: a high-performance in-memory approach",
      "year": 2017,
      "journal": "BMC bioinformatics",
      "volume": 18,
      "pages": 142,
      "pubMedIdentifier": 28249561,
      "author": [
        {
          "firstname": "Antonio",
          "surname": "Fabregat",
          "displayName": "Fabregat, A"
        },
        {
          "firstname": "Konstantinos",
          "surname": "Sidiropoulos",
          "displayName": "Sidiropoulos, K"
        },
        {
          "firstname": "Guilherme",
          "surname": "Viteri",
          "displayName": "Viteri, G"
        },
        {
          "firstname": "Oscar",
          "surname": "Forner",
          "displayName": "Forner, O"
        },
        {
          "firstname": "Pablo",
          "surname": "Marin-Garcia",
          "displayName": "Marin-Garcia, P"
        },
        {
          "firstname": "Vicente",
          "surname": "Arnau",
          "displayName": "Arnau, V"
        },
        {
          "firstname": "Peter",
          "surname": "D'Eustachio",
          "displayName": "D'Eustachio, P"
        },
        {
          "firstname": "Lincoln",
          "surname": "Stein",
          "displayName": "Stein, L"
        },
        {
          "firstname": "Henning",
          "surname": "Hermjakob",
          "displayName": "Hermjakob, H"
        }
      ]
    },
    {
      "year": 2017,
      "title": "Reactome enhanced pathway visualization",
      "journal": "Bioinformatics",
      "volume": 33,
      "pages": "3461-3467",
      "pubMedIdentifier": 29077811,
      "author": [
        {
          "firstname": "Konstantinos",
          "surname": "Sidiropoulos",
          "displayName": "Sidiropoulos, K"
        },
        {
          "firstname": "Guilherme",
          "surname": "Viteri",
          "displayName": "Viteri, G"
        },
        {
          "firstname": "Cristoffer",
          "surname": "Sevilla",
          "displayName": "Sevilla, C"
        },
        {
          "firstname": "Steve",
          "surname": "Jupe",
          "displayName": "Jupe, S"
        },
        {
          "firstname": "Marissa",
          "surname": "Webber",
          "displayName": "Webber, M"
        },
        {
          "firstname": "Marija",
          "surname": "Orlic-Milacic",
          "displayName": "Orlic-Milacic, M"
        },
        {
          "firstname": "Bijay",
          "surname": "Jassal",
          "displayName": "Jassal, B"
        },
        {
          "firstname": "Bruce",
          "surname": "May",
          "displayName": "May, B"
        },
        {
          "firstname": "Veronica",
          "surname": "Shamovsky",
          "displayName": "Shamovsky, V"
        },
        {
          "firstname": "Corina",
          "surname": "Duenas",
          "displayName": "Duenas, C"
        },
        {
          "firstname": "Karen",
          "surname": "Rothfels",
          "displayName": "Rothfels, K"
        },
        {
          "firstname": "Lisa",
          "surname": "Matthews",
          "displayName": "Matthews, L"
        },
        {
          "firstname": "Heeyeon",
          "surname": "Song",
          "displayName": "Song, H"
        },
        {
          "firstname": "Lincoln",
          "surname": "Stein",
          "displayName": "Stein, L"
        },
        {
          "firstname": "Robin",
          "surname": "Haw",
          "displayName": "Haw, R"
        },
        {
          "firstname": "Peter",
          "surname": "D'Eustachio",
          "displayName": "D'Eustachio, P"
        },
        {
          "firstname": "Peipei",
          "surname": "Ping",
          "displayName": "Ping, P"
        },
        {
          "firstname": "Henning",
          "surname": "Hermjakob",
          "displayName": "Hermjakob, H"
        },
        {
          "firstname": "Antonio",
          "surname": "Fabregat",
          "displayName": "Fabregat, A"
        }
      ]
    },
    {
      "title": "Reactome graph database: Efficient access to complex pathway data",
      "year": 2018,
      "journal": "PLoS computational biology",
      "volume": 14,
      "pages": "e1005968",
      "pubMedIdentifier": 29377902,
      "author": [
        {
          "firstname": "Antonio",
          "surname": "Fabregat",
          "displayName": "Fabregat, A"
        },
        {
          "firstname": "Florian",
          "surname": "Korninger",
          "displayName": "Korninger, F"
        },
        {
          "firstname": "Guilherme",
          "surname": "Viteri",
          "displayName": "Viteri, G"
        },
        {
          "firstname": "Konstantinos",
          "surname": "Sidiropoulos",
          "displayName": "Sidiropoulos, K"
        },
        {
          "firstname": "Pablo",
          "surname": "Marin-Garcia",
          "displayName": "Marin-Garcia, P"
        },
        {
          "firstname": "Peipei",
          "surname": "Ping",
          "displayName": "Ping, P"
        },
        {
          "firstname": "Guanming",
          "surname": "Wu",
          "displayName": "Wu, G"
        },
        {
          "firstname": "Lincoln",
          "surname": "Stein",
          "displayName": "Stein, L"
        },
        {
          "firstname": "Peter",
          "surname": "D'Eustachio",
          "displayName": "D'Eustachio, P"
        },
        {
          "firstname": "Henning",
          "surname": "Hermjakob",
          "displayName": "Hermjakob, H"
        }
      ]
    }
  ]
}